Metadata-Version: 2.1
Name: cdk-iamgenerator
Version: 1.0.4
Summary: This CDK Construct helps create IAM Managed Policies and IAM Roles using JSON Configuration
Home-page: https://github.com/srihariph/cdk-iam-generator.git
Author: Srihari Prabaharan<srihariph@gmail.com>
License: Apache-2.0
Project-URL: Source, https://github.com/srihariph/cdk-iam-generator.git
Platform: UNKNOWN
Classifier: Intended Audience :: Developers
Classifier: Operating System :: OS Independent
Classifier: Programming Language :: JavaScript
Classifier: Programming Language :: Python :: 3 :: Only
Classifier: Programming Language :: Python :: 3.6
Classifier: Programming Language :: Python :: 3.7
Classifier: Programming Language :: Python :: 3.8
Classifier: Typing :: Typed
Classifier: Development Status :: 5 - Production/Stable
Classifier: License :: OSI Approved
Requires-Python: >=3.6
